{"directed": false, "multigraph": false, "graph": [], "nodes": [{"graph": null, "nnodes": 2, "nedges": 1, "density": 1.0, "units": "[48, 36]", "population": 2, "D": 1, "R": 1, "init_part_1": 6, "init_part_2": 1, "init_part_3": 4, "id": 0}, {"graph": null, "nnodes": 2, "nedges": 1, "density": 1.0, "units": "[72, 60]", "population": 2, "D": 1, "R": 1, "init_part_1": 6, "init_part_2": 1, "init_part_3": 4, "id": 1}, {"graph": null, "nnodes": 2, "nedges": 1, "density": 1.0, "units": "[91, 103]", "population": 2, "D": 2, "R": 0, "init_part_1": 10, "init_part_2": 9, "init_part_3": 11, "id": 2}, {"graph": null, "nnodes": 2, "nedges": 1, "density": 1.0, "units": "[92, 93]", "population": 2, "D": 2, "R": 0, "init_part_1": 10, "init_part_2": 9, "init_part_3": 5, "id": 3}, {"graph": null, "nnodes": 2, "nedges": 1, "density": 1.0, "units": "[130, 118]", "population": 2, "D": 0, "R": 2, "init_part_1": 2, "init_part_2": 3, "init_part_3": 5, "id": 4}, {"graph": null, "nnodes": 2, "nedges": 1, "density": 1.0, "units": "[142, 143]", "population": 2, "D": 1, "R": 1, "init_part_1": 2, "init_part_2": 3, "init_part_3": 2, "id": 5}, {"graph": null, "nnodes": 2, "nedges": 1, "density": 1.0, "units": "[74, 62]", "population": 2, "D": 1, "R": 1, "init_part_1": 8, "init_part_2": 5, "init_part_3": 4, "id": 6}, {"graph": null, "nnodes": 2, "nedges": 1, "density": 1.0, "units": "[75, 76]", "population": 2, "D": 2, "R": 0, "init_part_1": 11, "init_part_2": 5, "init_part_3": 9, "id": 7}, {"graph": null, "nnodes": 2, "nedges": 1, "density": 1.0, "units": "[58, 59]", "population": 2, "D": 1, "R": 1, "init_part_1": 1, "init_part_2": 7, "init_part_3": 0, "id": 8}, {"graph": null, "nnodes": 2, "nedges": 1, "density": 1.0, "units": "[70, 71]", "population": 2, "D": 0, "R": 2, "init_part_1": 1, "init_part_2": 7, "init_part_3": 0, "id": 9}, {"graph": null, "nnodes": 2, "nedges": 1, "density": 1.0, "units": "[16, 4]", "population": 2, "D": 1, "R": 1, "init_part_1": 0, "init_part_2": 2, "init_part_3": 3, "id": 10}, {"graph": null, "nnodes": 2, "nedges": 1, "density": 1.0, "units": "[5, 6]", "population": 2, "D": 1, "R": 1, "init_part_1": 4, "init_part_2": 4, "init_part_3": 3, "id": 11}, {"graph": null, "nnodes": 2, "nedges": 1, "density": 1.0, "units": "[41, 42]", "population": 2, "D": 1, "R": 1, "init_part_1": 4, "init_part_2": 6, "init_part_3": 10, "id": 12}, {"graph": null, "nnodes": 2, "nedges": 1, "density": 1.0, "units": "[43, 55]", "population": 2, "D": 1, "R": 1, "init_part_1": 9, "init_part_2": 6, "init_part_3": 10, "id": 13}, {"graph": null, "nnodes": 2, "nedges": 1, "density": 1.0, "units": "[128, 129]", "population": 2, "D": 1, "R": 1, "init_part_1": 5, "init_part_2": 3, "init_part_3": 2, "id": 14}, {"graph": null, "nnodes": 2, "nedges": 1, "density": 1.0, "units": "[105, 117]", "population": 2, "D": 2, "R": 0, "init_part_1": 2, "init_part_2": 3, "init_part_3": 5, "id": 15}, {"graph": null, "nnodes": 2, "nedges": 1, "density": 1.0, "units": "[82, 83]", "population": 2, "D": 1, "R": 1, "init_part_1": 1, "init_part_2": 9, "init_part_3": 0, "id": 16}, {"graph": null, "nnodes": 2, "nedges": 1, "density": 1.0, "units": "[94, 95]", "population": 2, "D": 1, "R": 1, "init_part_1": 2, "init_part_2": 9, "init_part_3": 5, "id": 17}, {"graph": null, "nnodes": 2, "nedges": 1, "density": 1.0, "units": "[19, 7]", "population": 2, "D": 1, "R": 1, "init_part_1": 7, "init_part_2": 4, "init_part_3": 3, "id": 18}, {"graph": null, "nnodes": 2, "nedges": 1, "density": 1.0, "units": "[125, 126]", "population": 2, "D": 1, "R": 1, "init_part_1": 5, "init_part_2": 10, "init_part_3": 2, "id": 19}, {"graph": null, "nnodes": 2, "nedges": 1, "density": 1.0, "units": "[139, 127]", "population": 2, "D": 1, "R": 1, "init_part_1": 5, "init_part_2": 11, "init_part_3": 2, "id": 20}, {"graph": null, "nnodes": 2, "nedges": 1, "density": 1.0, "units": "[56, 68]", "population": 2, "D": 1, "R": 1, "init_part_1": 9, "init_part_2": 8, "init_part_3": 0, "id": 21}, {"graph": null, "nnodes": 2, "nedges": 1, "density": 1.0, "units": "[0, 1]", "population": 2, "D": 1, "R": 1, "init_part_1": 0, "init_part_2": 2, "init_part_3": 7, "id": 22}, {"graph": null, "nnodes": 2, "nedges": 1, "density": 1.0, "units": "[17, 18]", "population": 2, "D": 2, "R": 0, "init_part_1": 4, "init_part_2": 4, "init_part_3": 3, "id": 23}, {"graph": null, "nnodes": 2, "nedges": 1, "density": 1.0, "units": "[73, 61]", "population": 2, "D": 1, "R": 1, "init_part_1": 8, "init_part_2": 5, "init_part_3": 4, "id": 24}, {"graph": null, "nnodes": 2, "nedges": 1, "density": 1.0, "units": "[2, 3]", "population": 2, "D": 2, "R": 0, "init_part_1": 0, "init_part_2": 2, "init_part_3": 7, "id": 25}, {"graph": null, "nnodes": 2, "nedges": 1, "density": 1.0, "units": "[136, 124]", "population": 2, "D": 1, "R": 1, "init_part_1": 5, "init_part_2": 10, "init_part_3": 8, "id": 26}, {"graph": null, "nnodes": 2, "nedges": 1, "density": 1.0, "units": "[137, 138]", "population": 2, "D": 1, "R": 1, "init_part_1": 5, "init_part_2": 10, "init_part_3": 2, "id": 27}, {"graph": null, "nnodes": 2, "nedges": 1, "density": 1.0, "units": "[65, 66]", "population": 2, "D": 2, "R": 0, "init_part_1": 11, "init_part_2": 6, "init_part_3": 9, "id": 28}, {"graph": null, "nnodes": 2, "nedges": 1, "density": 1.0, "units": "[77, 78]", "population": 2, "D": 2, "R": 0, "init_part_1": 11, "init_part_2": 6, "init_part_3": 11, "id": 29}, {"graph": null, "nnodes": 2, "nedges": 1, "density": 1.0, "units": "[120, 132]", "population": 2, "D": 0, "R": 2, "init_part_1": 3, "init_part_2": 0, "init_part_3": 6, "id": 30}, {"graph": null, "nnodes": 2, "nedges": 1, "density": 1.0, "units": "[108, 109]", "population": 2, "D": 1, "R": 1, "init_part_1": 3, "init_part_2": 0, "init_part_3": 6, "id": 31}, {"graph": null, "nnodes": 2, "nedges": 1, "density": 1.0, "units": "[51, 39]", "population": 2, "D": 2, "R": 0, "init_part_1": 6, "init_part_2": 1, "init_part_3": 9, "id": 32}, {"graph": null, "nnodes": 2, "nedges": 1, "density": 1.0, "units": "[64, 63]", "population": 2, "D": 0, "R": 2, "init_part_1": 8, "init_part_2": 1, "init_part_3": 9, "id": 33}, {"graph": null, "nnodes": 2, "nedges": 1, "density": 1.0, "units": "[114, 115]", "population": 2, "D": 1, "R": 1, "init_part_1": 10, "init_part_2": 11, "init_part_3": 11, "id": 34}, {"graph": null, "nnodes": 2, "nedges": 1, "density": 1.0, "units": "[8, 9]", "population": 2, "D": 0, "R": 2, "init_part_1": 7, "init_part_2": 8, "init_part_3": 1, "id": 35}, {"graph": null, "nnodes": 2, "nedges": 1, "density": 1.0, "units": "[32, 20]", "population": 2, "D": 1, "R": 1, "init_part_1": 7, "init_part_2": 8, "init_part_3": 3, "id": 36}, {"graph": null, "nnodes": 2, "nedges": 1, "density": 1.0, "units": "[122, 134]", "population": 2, "D": 2, "R": 0, "init_part_1": 3, "init_part_2": 0, "init_part_3": 8, "id": 37}, {"graph": null, "nnodes": 2, "nedges": 1, "density": 1.0, "units": "[123, 135]", "population": 2, "D": 1, "R": 1, "init_part_1": 3, "init_part_2": 0, "init_part_3": 8, "id": 38}, {"graph": null, "nnodes": 2, "nedges": 1, "density": 1.0, "units": "[96, 84]", "population": 2, "D": 1, "R": 1, "init_part_1": 8, "init_part_2": 5, "init_part_3": 4, "id": 39}, {"graph": null, "nnodes": 2, "nedges": 1, "density": 1.0, "units": "[112, 100]", "population": 2, "D": 1, "R": 1, "init_part_1": 11, "init_part_2": 10, "init_part_3": 8, "id": 40}, {"graph": null, "nnodes": 2, "nedges": 1, "density": 1.0, "units": "[113, 101]", "population": 2, "D": 1, "R": 1, "init_part_1": 10, "init_part_2": 11, "init_part_3": 11, "id": 41}, {"graph": null, "nnodes": 2, "nedges": 1, "density": 1.0, "units": "[28, 29]", "population": 2, "D": 1, "R": 1, "init_part_1": 4, "init_part_2": 4, "init_part_3": 10, "id": 42}, {"graph": null, "nnodes": 2, "nedges": 1, "density": 1.0, "units": "[24, 12]", "population": 2, "D": 1, "R": 1, "init_part_1": 0, "init_part_2": 2, "init_part_3": 7, "id": 43}, {"graph": null, "nnodes": 2, "nedges": 1, "density": 1.0, "units": "[30, 31]", "population": 2, "D": 2, "R": 0, "init_part_1": 9, "init_part_2": 6, "init_part_3": 3, "id": 44}, {"graph": null, "nnodes": 2, "nedges": 1, "density": 1.0, "units": "[90, 102]", "population": 2, "D": 1, "R": 1, "init_part_1": 10, "init_part_2": 11, "init_part_3": 11, "id": 45}, {"graph": null, "nnodes": 2, "nedges": 1, "density": 1.0, "units": "[121, 133]", "population": 2, "D": 1, "R": 1, "init_part_1": 3, "init_part_2": 0, "init_part_3": 6, "id": 46}, {"graph": null, "nnodes": 2, "nedges": 1, "density": 1.0, "units": "[44, 45]", "population": 2, "D": 2, "R": 0, "init_part_1": 9, "init_part_2": 8, "init_part_3": 10, "id": 47}, {"graph": null, "nnodes": 2, "nedges": 1, "density": 1.0, "units": "[10, 11]", "population": 2, "D": 1, "R": 1, "init_part_1": 7, "init_part_2": 7, "init_part_3": 1, "id": 48}, {"graph": null, "nnodes": 2, "nedges": 1, "density": 1.0, "units": "[49, 50]", "population": 2, "D": 1, "R": 1, "init_part_1": 6, "init_part_2": 1, "init_part_3": 4, "id": 49}, {"graph": null, "nnodes": 2, "nedges": 1, "density": 1.0, "units": "[37, 38]", "population": 2, "D": 1, "R": 1, "init_part_1": 6, "init_part_2": 4, "init_part_3": 7, "id": 50}, {"graph": null, "nnodes": 2, "nedges": 1, "density": 1.0, "units": "[110, 111]", "population": 2, "D": 1, "R": 1, "init_part_1": 3, "init_part_2": 0, "init_part_3": 8, "id": 51}, {"graph": null, "nnodes": 2, "nedges": 1, "density": 1.0, "units": "[22, 23]", "population": 2, "D": 1, "R": 1, "init_part_1": 7, "init_part_2": 7, "init_part_3": 1, "id": 52}, {"graph": null, "nnodes": 2, "nedges": 1, "density": 1.0, "units": "[85, 86]", "population": 2, "D": 2, "R": 0, "init_part_1": 8, "init_part_2": 5, "init_part_3": 6, "id": 53}, {"graph": null, "nnodes": 2, "nedges": 1, "density": 1.0, "units": "[140, 141]", "population": 2, "D": 2, "R": 0, "init_part_1": 5, "init_part_2": 11, "init_part_3": 2, "id": 54}, {"graph": null, "nnodes": 2, "nedges": 1, "density": 1.0, "units": "[131, 119]", "population": 2, "D": 1, "R": 1, "init_part_1": 2, "init_part_2": 3, "init_part_3": 5, "id": 55}, {"graph": null, "nnodes": 2, "nedges": 1, "density": 1.0, "units": "[14, 15]", "population": 2, "D": 2, "R": 0, "init_part_1": 0, "init_part_2": 2, "init_part_3": 7, "id": 56}, {"graph": null, "nnodes": 2, "nedges": 1, "density": 1.0, "units": "[25, 13]", "population": 2, "D": 2, "R": 0, "init_part_1": 0, "init_part_2": 2, "init_part_3": 7, "id": 57}, {"graph": null, "nnodes": 2, "nedges": 1, "density": 1.0, "units": "[26, 27]", "population": 2, "D": 1, "R": 1, "init_part_1": 6, "init_part_2": 4, "init_part_3": 10, "id": 58}, {"graph": null, "nnodes": 2, "nedges": 1, "density": 1.0, "units": "[104, 116]", "population": 2, "D": 1, "R": 1, "init_part_1": 10, "init_part_2": 11, "init_part_3": 11, "id": 59}, {"graph": null, "nnodes": 2, "nedges": 1, "density": 1.0, "units": "[97, 98]", "population": 2, "D": 1, "R": 1, "init_part_1": 8, "init_part_2": 10, "init_part_3": 6, "id": 60}, {"graph": null, "nnodes": 2, "nedges": 1, "density": 1.0, "units": "[35, 47]", "population": 2, "D": 1, "R": 1, "init_part_1": 1, "init_part_2": 7, "init_part_3": 1, "id": 61}, {"graph": null, "nnodes": 2, "nedges": 1, "density": 1.0, "units": "[33, 21]", "population": 2, "D": 1, "R": 1, "init_part_1": 7, "init_part_2": 8, "init_part_3": 1, "id": 62}, {"graph": null, "nnodes": 2, "nedges": 1, "density": 1.0, "units": "[80, 81]", "population": 2, "D": 2, "R": 0, "init_part_1": 1, "init_part_2": 9, "init_part_3": 0, "id": 63}, {"graph": null, "nnodes": 2, "nedges": 1, "density": 1.0, "units": "[67, 79]", "population": 2, "D": 1, "R": 1, "init_part_1": 9, "init_part_2": 9, "init_part_3": 10, "id": 64}, {"graph": null, "nnodes": 2, "nedges": 1, "density": 1.0, "units": "[34, 46]", "population": 2, "D": 2, "R": 0, "init_part_1": 9, "init_part_2": 7, "init_part_3": 1, "id": 65}, {"graph": null, "nnodes": 2, "nedges": 1, "density": 1.0, "units": "[88, 89]", "population": 2, "D": 1, "R": 1, "init_part_1": 11, "init_part_2": 5, "init_part_3": 8, "id": 66}, {"graph": null, "nnodes": 2, "nedges": 1, "density": 1.0, "units": "[99, 87]", "population": 2, "D": 2, "R": 0, "init_part_1": 11, "init_part_2": 10, "init_part_3": 6, "id": 67}, {"graph": null, "nnodes": 2, "nedges": 1, "density": 1.0, "units": "[40, 52]", "population": 2, "D": 1, "R": 1, "init_part_1": 4, "init_part_2": 1, "init_part_3": 9, "id": 68}, {"graph": null, "nnodes": 2, "nedges": 1, "density": 1.0, "units": "[106, 107]", "population": 2, "D": 1, "R": 1, "init_part_1": 2, "init_part_2": 3, "init_part_3": 5, "id": 69}, {"graph": null, "nnodes": 2, "nedges": 1, "density": 1.0, "units": "[53, 54]", "population": 2, "D": 1, "R": 1, "init_part_1": 4, "init_part_2": 6, "init_part_3": 9, "id": 70}, {"graph": null, "nnodes": 2, "nedges": 1, "density": 1.0, "units": "[57, 69]", "population": 2, "D": 1, "R": 1, "init_part_1": 1, "init_part_2": 8, "init_part_3": 0, "id": 71}], "adjacency": [[{"weight": 1, "random_weight": 0.8569193543026907, "id": 1}, {"weight": 1, "random_weight": 0.9606685845632369, "id": 43}, {"weight": 1, "random_weight": 0.34555469980103104, "id": 49}, {"weight": 1, "random_weight": 0.9672380131691578, "id": 50}], [{"weight": 1, "random_weight": 0.8569193543026907, "id": 0}, {"weight": 2, "random_weight": 0.4062303725913521, "id": 24}, {"weight": 1, "random_weight": 0.001709182012996635, "id": 39}], [{"weight": 1, "random_weight": 0.15224506920693293, "id": 3}, {"weight": 1, "random_weight": 0.5542536142341541, "id": 34}, {"weight": 2, "random_weight": 0.6345085361071041, "id": 45}, {"weight": 1, "random_weight": 0.9792307095144432, "id": 59}, {"weight": 1, "random_weight": 0.8593813132227706, "id": 64}], [{"weight": 1, "random_weight": 0.15224506920693293, "id": 2}, {"weight": 1, "random_weight": 0.8500234247659245, "id": 15}, {"weight": 1, "random_weight": 0.37189069828375587, "id": 17}, {"weight": 1, "random_weight": 0.6289745772736566, "id": 59}, {"weight": 2, "random_weight": 0.4711352372166463, "id": 63}], [{"weight": 1, "random_weight": 0.6764685060119393, "id": 5}, {"weight": 1, "random_weight": 0.9090184256037277, "id": 14}, {"weight": 1, "random_weight": 0.22536233943879846, "id": 15}, {"weight": 2, "random_weight": 0.8179289360835614, "id": 55}, {"weight": 1, "random_weight": 0.6782052104711008, "id": 69}], [{"weight": 1, "random_weight": 0.6764685060119393, "id": 4}, {"weight": 1, "random_weight": 0.3320818376859248, "id": 54}, {"weight": 1, "random_weight": 0.9224161309391751, "id": 55}], [{"weight": 1, "random_weight": 0.676058176159991, "id": 7}, {"weight": 2, "random_weight": 0.7852518810436528, "id": 24}, {"weight": 1, "random_weight": 0.55195081487641, "id": 33}, {"weight": 1, "random_weight": 0.5234768529498336, "id": 49}, {"weight": 1, "random_weight": 0.8080430277751309, "id": 53}], [{"weight": 1, "random_weight": 0.676058176159991, "id": 6}, {"weight": 1, "random_weight": 0.9780830784962726, "id": 29}, {"weight": 2, "random_weight": 0.9420990123278592, "id": 33}, {"weight": 1, "random_weight": 0.9924629163155374, "id": 66}, {"weight": 1, "random_weight": 0.6626325052785735, "id": 67}], [{"weight": 2, "random_weight": 0.7118613920190792, "id": 9}, {"weight": 1, "random_weight": 0.9560304791851859, "id": 61}, {"weight": 1, "random_weight": 0.645452535718233, "id": 65}, {"weight": 1, "random_weight": 0.6088097893621197, "id": 71}], [{"weight": 2, "random_weight": 0.7118613920190792, "id": 8}, {"weight": 2, "random_weight": 0.9972577690002064, "id": 16}, {"weight": 1, "random_weight": 0.5020038759639063, "id": 71}], [{"weight": 1, "random_weight": 0.4903809914614278, "id": 11}, {"weight": 1, "random_weight": 0.41452160468020705, "id": 23}, {"weight": 1, "random_weight": 0.3900111067267983, "id": 25}, {"weight": 1, "random_weight": 0.5810989182284247, "id": 42}, {"weight": 1, "random_weight": 0.5215132923036425, "id": 56}], [{"weight": 1, "random_weight": 0.4903809914614278, "id": 10}, {"weight": 1, "random_weight": 0.27835470940831675, "id": 18}, {"weight": 2, "random_weight": 0.33982608800634073, "id": 23}], [{"weight": 1, "random_weight": 0.6267934703110287, "id": 13}, {"weight": 1, "random_weight": 0.276388752482298, "id": 42}, {"weight": 1, "random_weight": 0.6114869977196671, "id": 44}, {"weight": 1, "random_weight": 0.37861814173709607, "id": 68}, {"weight": 2, "random_weight": 0.5412042940676259, "id": 70}], [{"weight": 1, "random_weight": 0.6267934703110287, "id": 12}, {"weight": 1, "random_weight": 0.7164845841988242, "id": 21}, {"weight": 1, "random_weight": 0.5446880982718558, "id": 44}, {"weight": 1, "random_weight": 0.04018838052736273, "id": 47}, {"weight": 1, "random_weight": 0.8078820696908019, "id": 64}, {"weight": 1, "random_weight": 0.8927849936802528, "id": 70}], [{"weight": 1, "random_weight": 0.9090184256037277, "id": 4}, {"weight": 1, "random_weight": 0.6272193531554484, "id": 15}, {"weight": 1, "random_weight": 0.2621376636923698, "id": 20}, {"weight": 2, "random_weight": 0.13634550052388195, "id": 54}, {"weight": 1, "random_weight": 0.75636136123374, "id": 59}], [{"weight": 1, "random_weight": 0.8500234247659245, "id": 3}, {"weight": 1, "random_weight": 0.22536233943879846, "id": 4}, {"weight": 1, "random_weight": 0.6272193531554484, "id": 14}, {"weight": 2, "random_weight": 0.7399509145884743, "id": 59}, {"weight": 1, "random_weight": 0.4633364975491504, "id": 69}], [{"weight": 2, "random_weight": 0.9972577690002064, "id": 9}, {"weight": 2, "random_weight": 0.40809162742057936, "id": 17}, {"weight": 1, "random_weight": 0.20743518176255538, "id": 63}], [{"weight": 1, "random_weight": 0.37189069828375587, "id": 3}, {"weight": 2, "random_weight": 0.40809162742057936, "id": 16}, {"weight": 2, "random_weight": 0.5607176759772134, "id": 69}], [{"weight": 1, "random_weight": 0.27835470940831675, "id": 11}, {"weight": 1, "random_weight": 0.8375322485595961, "id": 23}, {"weight": 1, "random_weight": 0.9208477136822957, "id": 35}, {"weight": 1, "random_weight": 0.4939711539727206, "id": 36}, {"weight": 1, "random_weight": 0.6698151368684571, "id": 44}], [{"weight": 1, "random_weight": 0.9299227583222727, "id": 20}, {"weight": 1, "random_weight": 0.7698035278524477, "id": 26}, {"weight": 2, "random_weight": 0.572681781325454, "id": 27}, {"weight": 1, "random_weight": 0.6710112427029779, "id": 34}, {"weight": 1, "random_weight": 0.8299177500784658, "id": 41}], [{"weight": 1, "random_weight": 0.2621376636923698, "id": 14}, {"weight": 1, "random_weight": 0.9299227583222727, "id": 19}, {"weight": 1, "random_weight": 0.4021494601420641, "id": 27}, {"weight": 1, "random_weight": 0.08110740220164603, "id": 34}, {"weight": 1, "random_weight": 0.2954944103142618, "id": 54}], [{"weight": 1, "random_weight": 0.7164845841988242, "id": 13}, {"weight": 1, "random_weight": 0.5742936805496782, "id": 47}, {"weight": 1, "random_weight": 0.37087565893185637, "id": 63}, {"weight": 1, "random_weight": 0.5121582940387278, "id": 64}, {"weight": 2, "random_weight": 0.5755631404730878, "id": 71}], [{"weight": 1, "random_weight": 0.5202223910590071, "id": 25}, {"weight": 1, "random_weight": 0.25508488598694923, "id": 43}, {"weight": 1, "random_weight": 0.9982815314890431, "id": 57}], [{"weight": 1, "random_weight": 0.41452160468020705, "id": 10}, {"weight": 2, "random_weight": 0.33982608800634073, "id": 11}, {"weight": 1, "random_weight": 0.8375322485595961, "id": 18}, {"weight": 1, "random_weight": 0.9782760572056112, "id": 42}, {"weight": 1, "random_weight": 0.801132309246399, "id": 44}], [{"weight": 2, "random_weight": 0.4062303725913521, "id": 1}, {"weight": 2, "random_weight": 0.7852518810436528, "id": 6}, {"weight": 1, "random_weight": 0.19907086153358056, "id": 49}, {"weight": 1, "random_weight": 0.8648310500518787, "id": 53}], [{"weight": 1, "random_weight": 0.3900111067267983, "id": 10}, {"weight": 1, "random_weight": 0.5202223910590071, "id": 22}, {"weight": 2, "random_weight": 0.7391623186670141, "id": 56}], [{"weight": 1, "random_weight": 0.7698035278524477, "id": 19}, {"weight": 1, "random_weight": 0.4726148756969887, "id": 27}, {"weight": 2, "random_weight": 0.07097242598141418, "id": 38}, {"weight": 1, "random_weight": 0.9659986340255218, "id": 40}], [{"weight": 2, "random_weight": 0.572681781325454, "id": 19}, {"weight": 1, "random_weight": 0.4021494601420641, "id": 20}, {"weight": 1, "random_weight": 0.4726148756969887, "id": 26}], [{"weight": 2, "random_weight": 0.778739163076556, "id": 29}, {"weight": 1, "random_weight": 0.8451348061579635, "id": 33}, {"weight": 1, "random_weight": 0.9710744123700943, "id": 64}, {"weight": 2, "random_weight": 0.04722963148437709, "id": 70}], [{"weight": 1, "random_weight": 0.9780830784962726, "id": 7}, {"weight": 2, "random_weight": 0.778739163076556, "id": 28}, {"weight": 1, "random_weight": 0.1195695050946678, "id": 45}, {"weight": 1, "random_weight": 0.21618274028403683, "id": 64}, {"weight": 1, "random_weight": 0.28343510543668904, "id": 66}], [{"weight": 1, "random_weight": 0.25346584630007785, "id": 31}, {"weight": 2, "random_weight": 0.6353777296846467, "id": 46}], [{"weight": 1, "random_weight": 0.25346584630007785, "id": 30}, {"weight": 1, "random_weight": 0.8133656808607088, "id": 39}, {"weight": 1, "random_weight": 0.2573226271406136, "id": 46}, {"weight": 1, "random_weight": 0.5009036258220244, "id": 51}, {"weight": 1, "random_weight": 0.03954964391401339, "id": 60}], [{"weight": 1, "random_weight": 0.23422554029742648, "id": 33}, {"weight": 1, "random_weight": 0.5687996492008727, "id": 49}, {"weight": 1, "random_weight": 0.6514894933797927, "id": 50}, {"weight": 1, "random_weight": 0.13243817650575507, "id": 58}, {"weight": 2, "random_weight": 0.02027654445520377, "id": 68}], [{"weight": 1, "random_weight": 0.55195081487641, "id": 6}, {"weight": 2, "random_weight": 0.9420990123278592, "id": 7}, {"weight": 1, "random_weight": 0.8451348061579635, "id": 28}, {"weight": 1, "random_weight": 0.23422554029742648, "id": 32}, {"weight": 1, "random_weight": 0.40821344594006115, "id": 68}], [{"weight": 1, "random_weight": 0.5542536142341541, "id": 2}, {"weight": 1, "random_weight": 0.6710112427029779, "id": 19}, {"weight": 1, "random_weight": 0.08110740220164603, "id": 20}, {"weight": 1, "random_weight": 0.35375200803295237, "id": 41}, {"weight": 1, "random_weight": 0.11748332575785436, "id": 45}, {"weight": 1, "random_weight": 0.32001413743065454, "id": 59}], [{"weight": 1, "random_weight": 0.9208477136822957, "id": 18}, {"weight": 1, "random_weight": 0.47512539063342807, "id": 36}, {"weight": 1, "random_weight": 0.6136921673198691, "id": 48}, {"weight": 1, "random_weight": 0.4317176988779542, "id": 62}], [{"weight": 1, "random_weight": 0.4939711539727206, "id": 18}, {"weight": 1, "random_weight": 0.47512539063342807, "id": 35}, {"weight": 1, "random_weight": 0.23913746525983548, "id": 44}, {"weight": 1, "random_weight": 0.7296008570279926, "id": 47}, {"weight": 2, "random_weight": 0.3767355366397822, "id": 62}], [{"weight": 2, "random_weight": 0.6273563920258515, "id": 38}, {"weight": 2, "random_weight": 0.2885795126029409, "id": 46}, {"weight": 1, "random_weight": 0.7930471936334573, "id": 51}], [{"weight": 2, "random_weight": 0.07097242598141418, "id": 26}, {"weight": 2, "random_weight": 0.6273563920258515, "id": 37}, {"weight": 1, "random_weight": 0.39679039901279456, "id": 51}], [{"weight": 1, "random_weight": 0.001709182012996635, "id": 1}, {"weight": 1, "random_weight": 0.8133656808607088, "id": 31}, {"weight": 1, "random_weight": 0.6547667825811787, "id": 53}, {"weight": 1, "random_weight": 0.047652048739894926, "id": 60}], [{"weight": 1, "random_weight": 0.9659986340255218, "id": 26}, {"weight": 2, "random_weight": 0.35127894592584874, "id": 41}, {"weight": 1, "random_weight": 0.35639141980674793, "id": 51}, {"weight": 1, "random_weight": 0.28966851645205605, "id": 66}, {"weight": 1, "random_weight": 0.45195594759463165, "id": 67}], [{"weight": 1, "random_weight": 0.8299177500784658, "id": 19}, {"weight": 1, "random_weight": 0.35375200803295237, "id": 34}, {"weight": 2, "random_weight": 0.35127894592584874, "id": 40}, {"weight": 1, "random_weight": 0.56244152928806, "id": 45}, {"weight": 1, "random_weight": 0.6528987707867682, "id": 66}], [{"weight": 1, "random_weight": 0.5810989182284247, "id": 10}, {"weight": 1, "random_weight": 0.276388752482298, "id": 12}, {"weight": 1, "random_weight": 0.9782760572056112, "id": 23}, {"weight": 1, "random_weight": 0.6352237446165983, "id": 44}, {"weight": 1, "random_weight": 0.4127401770262694, "id": 58}, {"weight": 1, "random_weight": 0.48475698266747935, "id": 68}], [{"weight": 1, "random_weight": 0.9606685845632369, "id": 0}, {"weight": 1, "random_weight": 0.25508488598694923, "id": 22}, {"weight": 2, "random_weight": 0.022416826356660757, "id": 57}], [{"weight": 1, "random_weight": 0.6114869977196671, "id": 12}, {"weight": 1, "random_weight": 0.5446880982718558, "id": 13}, {"weight": 1, "random_weight": 0.6698151368684571, "id": 18}, {"weight": 1, "random_weight": 0.801132309246399, "id": 23}, {"weight": 1, "random_weight": 0.23913746525983548, "id": 36}, {"weight": 1, "random_weight": 0.6352237446165983, "id": 42}], [{"weight": 2, "random_weight": 0.6345085361071041, "id": 2}, {"weight": 1, "random_weight": 0.1195695050946678, "id": 29}, {"weight": 1, "random_weight": 0.11748332575785436, "id": 34}, {"weight": 1, "random_weight": 0.56244152928806, "id": 41}, {"weight": 1, "random_weight": 0.5769262778528954, "id": 66}], [{"weight": 2, "random_weight": 0.6353777296846467, "id": 30}, {"weight": 1, "random_weight": 0.2573226271406136, "id": 31}, {"weight": 2, "random_weight": 0.2885795126029409, "id": 37}], [{"weight": 1, "random_weight": 0.04018838052736273, "id": 13}, {"weight": 1, "random_weight": 0.5742936805496782, "id": 21}, {"weight": 1, "random_weight": 0.7296008570279926, "id": 36}, {"weight": 1, "random_weight": 0.4785848155287885, "id": 62}, {"weight": 1, "random_weight": 0.4259300621039209, "id": 65}, {"weight": 1, "random_weight": 0.9690801646622088, "id": 71}], [{"weight": 1, "random_weight": 0.6136921673198691, "id": 35}, {"weight": 2, "random_weight": 0.23785802569756764, "id": 52}], [{"weight": 1, "random_weight": 0.34555469980103104, "id": 0}, {"weight": 1, "random_weight": 0.5234768529498336, "id": 6}, {"weight": 1, "random_weight": 0.19907086153358056, "id": 24}, {"weight": 1, "random_weight": 0.5687996492008727, "id": 32}, {"weight": 2, "random_weight": 0.9326300514639924, "id": 50}], [{"weight": 1, "random_weight": 0.9672380131691578, "id": 0}, {"weight": 1, "random_weight": 0.6514894933797927, "id": 32}, {"weight": 2, "random_weight": 0.9326300514639924, "id": 49}, {"weight": 1, "random_weight": 0.4519912370571565, "id": 57}, {"weight": 1, "random_weight": 0.8333005046079089, "id": 58}], [{"weight": 1, "random_weight": 0.5009036258220244, "id": 31}, {"weight": 1, "random_weight": 0.7930471936334573, "id": 37}, {"weight": 1, "random_weight": 0.39679039901279456, "id": 38}, {"weight": 1, "random_weight": 0.35639141980674793, "id": 40}, {"weight": 1, "random_weight": 0.5259718166814398, "id": 60}, {"weight": 1, "random_weight": 0.5819095691741156, "id": 67}], [{"weight": 2, "random_weight": 0.23785802569756764, "id": 48}, {"weight": 1, "random_weight": 0.45930437594240003, "id": 61}, {"weight": 1, "random_weight": 0.45517034696080405, "id": 62}, {"weight": 1, "random_weight": 0.7450552735049082, "id": 65}], [{"weight": 1, "random_weight": 0.8080430277751309, "id": 6}, {"weight": 1, "random_weight": 0.8648310500518787, "id": 24}, {"weight": 1, "random_weight": 0.6547667825811787, "id": 39}, {"weight": 2, "random_weight": 0.7761090684468567, "id": 60}, {"weight": 1, "random_weight": 0.6357810757680736, "id": 67}], [{"weight": 1, "random_weight": 0.3320818376859248, "id": 5}, {"weight": 2, "random_weight": 0.13634550052388195, "id": 14}, {"weight": 1, "random_weight": 0.2954944103142618, "id": 20}], [{"weight": 2, "random_weight": 0.8179289360835614, "id": 4}, {"weight": 1, "random_weight": 0.9224161309391751, "id": 5}, {"weight": 1, "random_weight": 0.45431323412361324, "id": 69}], [{"weight": 1, "random_weight": 0.5215132923036425, "id": 10}, {"weight": 2, "random_weight": 0.7391623186670141, "id": 25}, {"weight": 1, "random_weight": 0.26125429308698156, "id": 57}, {"weight": 2, "random_weight": 0.5415649299827722, "id": 58}], [{"weight": 1, "random_weight": 0.9982815314890431, "id": 22}, {"weight": 2, "random_weight": 0.022416826356660757, "id": 43}, {"weight": 1, "random_weight": 0.4519912370571565, "id": 50}, {"weight": 1, "random_weight": 0.26125429308698156, "id": 56}, {"weight": 1, "random_weight": 0.018646831567904698, "id": 58}], [{"weight": 1, "random_weight": 0.13243817650575507, "id": 32}, {"weight": 1, "random_weight": 0.4127401770262694, "id": 42}, {"weight": 1, "random_weight": 0.8333005046079089, "id": 50}, {"weight": 2, "random_weight": 0.5415649299827722, "id": 56}, {"weight": 1, "random_weight": 0.018646831567904698, "id": 57}], [{"weight": 1, "random_weight": 0.9792307095144432, "id": 2}, {"weight": 1, "random_weight": 0.6289745772736566, "id": 3}, {"weight": 1, "random_weight": 0.75636136123374, "id": 14}, {"weight": 2, "random_weight": 0.7399509145884743, "id": 15}, {"weight": 1, "random_weight": 0.32001413743065454, "id": 34}], [{"weight": 1, "random_weight": 0.03954964391401339, "id": 31}, {"weight": 1, "random_weight": 0.047652048739894926, "id": 39}, {"weight": 1, "random_weight": 0.5259718166814398, "id": 51}, {"weight": 2, "random_weight": 0.7761090684468567, "id": 53}, {"weight": 1, "random_weight": 0.3209800383797403, "id": 67}], [{"weight": 1, "random_weight": 0.9560304791851859, "id": 8}, {"weight": 1, "random_weight": 0.45930437594240003, "id": 52}, {"weight": 2, "random_weight": 0.5229548237604692, "id": 65}], [{"weight": 1, "random_weight": 0.4317176988779542, "id": 35}, {"weight": 2, "random_weight": 0.3767355366397822, "id": 36}, {"weight": 1, "random_weight": 0.4785848155287885, "id": 47}, {"weight": 1, "random_weight": 0.45517034696080405, "id": 52}, {"weight": 1, "random_weight": 0.042954050560669366, "id": 65}], [{"weight": 2, "random_weight": 0.4711352372166463, "id": 3}, {"weight": 1, "random_weight": 0.20743518176255538, "id": 16}, {"weight": 1, "random_weight": 0.37087565893185637, "id": 21}, {"weight": 1, "random_weight": 0.5824408648269589, "id": 64}, {"weight": 1, "random_weight": 0.9968347597552161, "id": 71}], [{"weight": 1, "random_weight": 0.8593813132227706, "id": 2}, {"weight": 1, "random_weight": 0.8078820696908019, "id": 13}, {"weight": 1, "random_weight": 0.5121582940387278, "id": 21}, {"weight": 1, "random_weight": 0.9710744123700943, "id": 28}, {"weight": 1, "random_weight": 0.21618274028403683, "id": 29}, {"weight": 1, "random_weight": 0.5824408648269589, "id": 63}], [{"weight": 1, "random_weight": 0.645452535718233, "id": 8}, {"weight": 1, "random_weight": 0.4259300621039209, "id": 47}, {"weight": 1, "random_weight": 0.7450552735049082, "id": 52}, {"weight": 2, "random_weight": 0.5229548237604692, "id": 61}, {"weight": 1, "random_weight": 0.042954050560669366, "id": 62}], [{"weight": 1, "random_weight": 0.9924629163155374, "id": 7}, {"weight": 1, "random_weight": 0.28343510543668904, "id": 29}, {"weight": 1, "random_weight": 0.28966851645205605, "id": 40}, {"weight": 1, "random_weight": 0.6528987707867682, "id": 41}, {"weight": 1, "random_weight": 0.5769262778528954, "id": 45}, {"weight": 1, "random_weight": 0.582501390138484, "id": 67}], [{"weight": 1, "random_weight": 0.6626325052785735, "id": 7}, {"weight": 1, "random_weight": 0.45195594759463165, "id": 40}, {"weight": 1, "random_weight": 0.5819095691741156, "id": 51}, {"weight": 1, "random_weight": 0.6357810757680736, "id": 53}, {"weight": 1, "random_weight": 0.3209800383797403, "id": 60}, {"weight": 1, "random_weight": 0.582501390138484, "id": 66}], [{"weight": 1, "random_weight": 0.37861814173709607, "id": 12}, {"weight": 2, "random_weight": 0.02027654445520377, "id": 32}, {"weight": 1, "random_weight": 0.40821344594006115, "id": 33}, {"weight": 1, "random_weight": 0.48475698266747935, "id": 42}, {"weight": 1, "random_weight": 0.14391118967898753, "id": 70}], [{"weight": 1, "random_weight": 0.6782052104711008, "id": 4}, {"weight": 1, "random_weight": 0.4633364975491504, "id": 15}, {"weight": 2, "random_weight": 0.5607176759772134, "id": 17}, {"weight": 1, "random_weight": 0.45431323412361324, "id": 55}], [{"weight": 2, "random_weight": 0.5412042940676259, "id": 12}, {"weight": 1, "random_weight": 0.8927849936802528, "id": 13}, {"weight": 2, "random_weight": 0.04722963148437709, "id": 28}, {"weight": 1, "random_weight": 0.14391118967898753, "id": 68}], [{"weight": 1, "random_weight": 0.6088097893621197, "id": 8}, {"weight": 1, "random_weight": 0.5020038759639063, "id": 9}, {"weight": 2, "random_weight": 0.5755631404730878, "id": 21}, {"weight": 1, "random_weight": 0.9690801646622088, "id": 47}, {"weight": 1, "random_weight": 0.9968347597552161, "id": 63}]]}