{"directed": false, "multigraph": false, "graph": [], "nodes": [{"graph": null, "nnodes": 6, "nedges": 5, "density": 0.3333333333333333, "units": "[100, 101, 113, 114, 115, 116]", "population": 6, "D": 3, "R": 3, "init_part_1": 7, "init_part_2": 3, "init_part_3": 7, "id": 0}, {"graph": null, "nnodes": 6, "nedges": 6, "density": 0.4, "units": "[137, 138, 112, 124, 125, 126]", "population": 6, "D": 3, "R": 3, "init_part_1": 7, "init_part_2": 1, "init_part_3": 2, "id": 1}, {"graph": null, "nnodes": 6, "nedges": 7, "density": 0.4666666666666667, "units": "[128, 129, 139, 140, 141, 127]", "population": 6, "D": 2, "R": 4, "init_part_1": 3, "init_part_2": 1, "init_part_3": 4, "id": 2}, {"graph": null, "nnodes": 6, "nedges": 6, "density": 0.4, "units": "[106, 107, 83, 119, 94, 95]", "population": 6, "D": 3, "R": 3, "init_part_1": 1, "init_part_2": 2, "init_part_3": 10, "id": 3}, {"graph": null, "nnodes": 6, "nedges": 7, "density": 0.4666666666666667, "units": "[104, 105, 80, 81, 92, 93]", "population": 6, "D": 2, "R": 4, "init_part_1": 1, "init_part_2": 2, "init_part_3": 11, "id": 4}, {"graph": null, "nnodes": 6, "nedges": 5, "density": 0.3333333333333333, "units": "[96, 132, 133, 134, 108, 120]", "population": 6, "D": 3, "R": 3, "init_part_1": 8, "init_part_2": 6, "init_part_3": 0, "id": 5}, {"graph": null, "nnodes": 6, "nedges": 6, "density": 0.4, "units": "[72, 73, 48, 84, 60, 61]", "population": 6, "D": 2, "R": 4, "init_part_1": 6, "init_part_2": 9, "init_part_3": 0, "id": 6}, {"graph": null, "nnodes": 6, "nedges": 5, "density": 0.3333333333333333, "units": "[99, 102, 87, 88, 89, 90]", "population": 6, "D": 3, "R": 3, "init_part_1": 9, "init_part_2": 8, "init_part_3": 7, "id": 7}, {"graph": null, "nnodes": 6, "nedges": 7, "density": 0.4666666666666667, "units": "[64, 74, 75, 76, 62, 63]", "population": 6, "D": 4, "R": 2, "init_part_1": 10, "init_part_2": 9, "init_part_3": 1, "id": 8}, {"graph": null, "nnodes": 6, "nedges": 5, "density": 0.3333333333333333, "units": "[65, 41, 77, 53, 29, 30]", "population": 6, "D": 3, "R": 3, "init_part_1": 10, "init_part_2": 11, "init_part_3": 8, "id": 9}, {"graph": null, "nnodes": 6, "nedges": 5, "density": 0.3333333333333333, "units": "[66, 103, 78, 79, 54, 91]", "population": 6, "D": 2, "R": 4, "init_part_1": 0, "init_part_2": 11, "init_part_3": 11, "id": 10}, {"graph": null, "nnodes": 6, "nedges": 7, "density": 0.4666666666666667, "units": "[39, 40, 51, 52, 27, 28]", "population": 6, "D": 3, "R": 3, "init_part_1": 11, "init_part_2": 4, "init_part_3": 5, "id": 11}, {"graph": null, "nnodes": 6, "nedges": 6, "density": 0.4, "units": "[130, 131, 142, 143, 117, 118]", "population": 6, "D": 4, "R": 2, "init_part_1": 3, "init_part_2": 3, "init_part_3": 4, "id": 12}, {"graph": null, "nnodes": 6, "nedges": 6, "density": 0.4, "units": "[0, 1, 12, 13, 25, 26]", "population": 6, "D": 4, "R": 2, "init_part_1": 11, "init_part_2": 5, "init_part_3": 3, "id": 13}, {"graph": null, "nnodes": 6, "nedges": 7, "density": 0.4666666666666667, "units": "[2, 3, 4, 14, 15, 16]", "population": 6, "D": 4, "R": 2, "init_part_1": 5, "init_part_2": 4, "init_part_3": 5, "id": 14}, {"graph": null, "nnodes": 6, "nedges": 6, "density": 0.4, "units": "[36, 37, 38, 49, 50, 24]", "population": 6, "D": 3, "R": 3, "init_part_1": 6, "init_part_2": 5, "init_part_3": 3, "id": 15}, {"graph": null, "nnodes": 6, "nedges": 5, "density": 0.3333333333333333, "units": "[34, 69, 70, 46, 82, 58]", "population": 6, "D": 3, "R": 3, "init_part_1": 4, "init_part_2": 10, "init_part_3": 10, "id": 16}, {"graph": null, "nnodes": 6, "nedges": 5, "density": 0.3333333333333333, "units": "[35, 71, 47, 22, 23, 59]", "population": 6, "D": 3, "R": 3, "init_part_1": 2, "init_part_2": 0, "init_part_3": 9, "id": 17}, {"graph": null, "nnodes": 6, "nedges": 7, "density": 0.4666666666666667, "units": "[5, 6, 7, 17, 18, 19]", "population": 6, "D": 3, "R": 3, "init_part_1": 5, "init_part_2": 7, "init_part_3": 6, "id": 18}, {"graph": null, "nnodes": 6, "nedges": 6, "density": 0.4, "units": "[8, 9, 10, 11, 20, 21]", "population": 6, "D": 4, "R": 2, "init_part_1": 2, "init_part_2": 0, "init_part_3": 9, "id": 19}, {"graph": null, "nnodes": 6, "nedges": 6, "density": 0.4, "units": "[32, 33, 44, 45, 57, 31]", "population": 6, "D": 3, "R": 3, "init_part_1": 4, "init_part_2": 7, "init_part_3": 6, "id": 20}, {"graph": null, "nnodes": 6, "nedges": 5, "density": 0.3333333333333333, "units": "[135, 136, 111, 121, 122, 123]", "population": 6, "D": 3, "R": 3, "init_part_1": 8, "init_part_2": 6, "init_part_3": 2, "id": 21}, {"graph": null, "nnodes": 6, "nedges": 6, "density": 0.4, "units": "[67, 68, 42, 43, 55, 56]", "population": 6, "D": 2, "R": 4, "init_part_1": 0, "init_part_2": 10, "init_part_3": 8, "id": 22}, {"graph": null, "nnodes": 6, "nedges": 7, "density": 0.4666666666666667, "units": "[97, 98, 109, 110, 85, 86]", "population": 6, "D": 3, "R": 3, "init_part_1": 9, "init_part_2": 8, "init_part_3": 1, "id": 23}], "adjacency": [[{"weight": 4, "random_weight": 0.713237702123074, "id": 1}, {"weight": 2, "random_weight": 0.19142119985605743, "id": 2}, {"weight": 1, "random_weight": 0.7806709110563086, "id": 4}, {"weight": 5, "random_weight": 0.6012905566321535, "id": 7}, {"weight": 1, "random_weight": 0.9004820514716355, "id": 10}, {"weight": 1, "random_weight": 0.8738573618673667, "id": 12}], [{"weight": 4, "random_weight": 0.713237702123074, "id": 0}, {"weight": 2, "random_weight": 0.19742772721793345, "id": 2}, {"weight": 4, "random_weight": 0.5822095304652468, "id": 21}], [{"weight": 2, "random_weight": 0.19142119985605743, "id": 0}, {"weight": 2, "random_weight": 0.19742772721793345, "id": 1}, {"weight": 3, "random_weight": 0.09917734475661033, "id": 12}], [{"weight": 2, "random_weight": 0.8860979659388861, "id": 4}, {"weight": 3, "random_weight": 0.6440307040834005, "id": 12}, {"weight": 2, "random_weight": 0.20273520020403135, "id": 16}, {"weight": 1, "random_weight": 0.7918144220398099, "id": 17}], [{"weight": 1, "random_weight": 0.7806709110563086, "id": 0}, {"weight": 2, "random_weight": 0.8860979659388861, "id": 3}, {"weight": 3, "random_weight": 0.4896559531992737, "id": 10}, {"weight": 1, "random_weight": 0.9338489509139986, "id": 12}, {"weight": 2, "random_weight": 0.44153074806596593, "id": 16}, {"weight": 1, "random_weight": 0.6121658681423612, "id": 22}], [{"weight": 1, "random_weight": 0.041306965565347076, "id": 6}, {"weight": 4, "random_weight": 0.9127875678901128, "id": 21}, {"weight": 2, "random_weight": 0.5537722152509406, "id": 23}], [{"weight": 1, "random_weight": 0.041306965565347076, "id": 5}, {"weight": 2, "random_weight": 0.02759118419203499, "id": 8}, {"weight": 3, "random_weight": 0.5829816485626, "id": 15}, {"weight": 2, "random_weight": 0.509102177799056, "id": 23}], [{"weight": 5, "random_weight": 0.6012905566321535, "id": 0}, {"weight": 2, "random_weight": 0.6424948661733098, "id": 8}, {"weight": 1, "random_weight": 0.3029153508264828, "id": 9}, {"weight": 3, "random_weight": 0.9320278529856324, "id": 10}, {"weight": 1, "random_weight": 0.6972272188438833, "id": 21}, {"weight": 2, "random_weight": 0.35055958912829965, "id": 23}], [{"weight": 2, "random_weight": 0.02759118419203499, "id": 6}, {"weight": 2, "random_weight": 0.6424948661733098, "id": 7}, {"weight": 2, "random_weight": 0.5379016409556013, "id": 9}, {"weight": 2, "random_weight": 0.015950170431492716, "id": 11}, {"weight": 1, "random_weight": 0.8621846157943732, "id": 15}, {"weight": 1, "random_weight": 0.041280725296446, "id": 23}], [{"weight": 1, "random_weight": 0.3029153508264828, "id": 7}, {"weight": 2, "random_weight": 0.5379016409556013, "id": 8}, {"weight": 3, "random_weight": 0.28681746008077114, "id": 10}, {"weight": 3, "random_weight": 0.6565980963246064, "id": 11}, {"weight": 2, "random_weight": 0.8778596720773099, "id": 18}, {"weight": 1, "random_weight": 0.7992644586176656, "id": 20}, {"weight": 2, "random_weight": 0.09866647274985785, "id": 22}], [{"weight": 1, "random_weight": 0.9004820514716355, "id": 0}, {"weight": 3, "random_weight": 0.4896559531992737, "id": 4}, {"weight": 3, "random_weight": 0.9320278529856324, "id": 7}, {"weight": 3, "random_weight": 0.28681746008077114, "id": 9}, {"weight": 4, "random_weight": 0.3991982034960462, "id": 22}], [{"weight": 2, "random_weight": 0.015950170431492716, "id": 8}, {"weight": 3, "random_weight": 0.6565980963246064, "id": 9}, {"weight": 1, "random_weight": 0.23817588154583547, "id": 13}, {"weight": 2, "random_weight": 0.34035073093640555, "id": 14}, {"weight": 2, "random_weight": 0.27699429073418047, "id": 15}], [{"weight": 1, "random_weight": 0.8738573618673667, "id": 0}, {"weight": 3, "random_weight": 0.09917734475661033, "id": 2}, {"weight": 3, "random_weight": 0.6440307040834005, "id": 3}, {"weight": 1, "random_weight": 0.9338489509139986, "id": 4}], [{"weight": 1, "random_weight": 0.23817588154583547, "id": 11}, {"weight": 3, "random_weight": 0.6115826776415221, "id": 14}, {"weight": 4, "random_weight": 0.12979205750347544, "id": 15}], [{"weight": 2, "random_weight": 0.34035073093640555, "id": 11}, {"weight": 3, "random_weight": 0.6115826776415221, "id": 13}, {"weight": 2, "random_weight": 0.7950007914084923, "id": 18}], [{"weight": 3, "random_weight": 0.5829816485626, "id": 6}, {"weight": 1, "random_weight": 0.8621846157943732, "id": 8}, {"weight": 2, "random_weight": 0.27699429073418047, "id": 11}, {"weight": 4, "random_weight": 0.12979205750347544, "id": 13}], [{"weight": 2, "random_weight": 0.20273520020403135, "id": 3}, {"weight": 2, "random_weight": 0.44153074806596593, "id": 4}, {"weight": 5, "random_weight": 0.9290439646372904, "id": 17}, {"weight": 4, "random_weight": 0.5835355894933874, "id": 20}, {"weight": 1, "random_weight": 0.7020946835050821, "id": 22}], [{"weight": 1, "random_weight": 0.7918144220398099, "id": 3}, {"weight": 5, "random_weight": 0.9290439646372904, "id": 16}, {"weight": 3, "random_weight": 0.6771335509339451, "id": 19}], [{"weight": 2, "random_weight": 0.8778596720773099, "id": 9}, {"weight": 2, "random_weight": 0.7950007914084923, "id": 14}, {"weight": 2, "random_weight": 0.7047525671276261, "id": 19}, {"weight": 1, "random_weight": 0.26330598031642494, "id": 20}], [{"weight": 3, "random_weight": 0.6771335509339451, "id": 17}, {"weight": 2, "random_weight": 0.7047525671276261, "id": 18}, {"weight": 2, "random_weight": 0.1396578252728783, "id": 20}], [{"weight": 1, "random_weight": 0.7992644586176656, "id": 9}, {"weight": 4, "random_weight": 0.5835355894933874, "id": 16}, {"weight": 1, "random_weight": 0.26330598031642494, "id": 18}, {"weight": 2, "random_weight": 0.1396578252728783, "id": 19}, {"weight": 4, "random_weight": 0.5964821375621481, "id": 22}], [{"weight": 4, "random_weight": 0.5822095304652468, "id": 1}, {"weight": 4, "random_weight": 0.9127875678901128, "id": 5}, {"weight": 1, "random_weight": 0.6972272188438833, "id": 7}, {"weight": 3, "random_weight": 0.7271552042076987, "id": 23}], [{"weight": 1, "random_weight": 0.6121658681423612, "id": 4}, {"weight": 2, "random_weight": 0.09866647274985785, "id": 9}, {"weight": 4, "random_weight": 0.3991982034960462, "id": 10}, {"weight": 1, "random_weight": 0.7020946835050821, "id": 16}, {"weight": 4, "random_weight": 0.5964821375621481, "id": 20}], [{"weight": 2, "random_weight": 0.5537722152509406, "id": 5}, {"weight": 2, "random_weight": 0.509102177799056, "id": 6}, {"weight": 2, "random_weight": 0.35055958912829965, "id": 7}, {"weight": 1, "random_weight": 0.041280725296446, "id": 8}, {"weight": 3, "random_weight": 0.7271552042076987, "id": 21}]]}